upath/__init__.py
upath/core.py
upath/errors.py
upath/registry.py
upath/implementations/__init__.py
upath/implementations/gcs.py
upath/implementations/hdfs.py
upath/implementations/http.py
upath/implementations/memory.py
upath/implementations/s3.py
upath/tests/__init__.py
upath/tests/cases.py
upath/tests/conftest.py
upath/tests/test_core.py
upath/tests/implementations/__init__.py
upath/tests/implementations/test_gcs.py
upath/tests/implementations/test_hdfs.py
upath/tests/implementations/test_http.py
upath/tests/implementations/test_memory.py
upath/tests/implementations/test_s3.py
universal_pathlib_edge-0.0.13.dist-info/LICENSE
universal_pathlib_edge-0.0.13.dist-info/WHEEL
universal_pathlib_edge-0.0.13.dist-info/METADATA
universal_pathlib_edge-0.0.13.dist-info/RECORD
